aiohttp_cors/__about__.py
aiohttp_cors/__init__.py
aiohttp_cors/abc.py
aiohttp_cors/cors_config.py
aiohttp_cors/mixin.py
aiohttp_cors/preflight_handler.py
aiohttp_cors/py.typed
aiohttp_cors/resource_options.py
aiohttp_cors/urldispatcher_router_adapter.py
aiohttp_cors-0.8.0.dist-info/LICENSE
aiohttp_cors-0.8.0.dist-info/METADATA
aiohttp_cors-0.8.0.dist-info/WHEEL
aiohttp_cors-0.8.0.dist-info/top_level.txt
aiohttp_cors-0.8.0.dist-info/RECORD
