Metadata-Version: 2.2
Name: aiohttp-cors
Version: 0.8.0
Summary: CORS support for aiohttp
Home-page: https://github.com/aio-libs/aiohttp-cors
Author: Vladimir Rutsky and aio-libs team
Author-email: vladimir@rutsky.org
License: Apache License, Version 2.0
Classifier: License :: OSI Approved :: Apache Software License
Classifier: Intended Audience :: Developers
Classifier: Programming Language :: Python
Classifier: Programming Language :: Python :: 3
Classifier: Topic :: Software Development :: Libraries
Classifier: Topic :: Internet :: WWW/HTTP
Classifier: Framework :: AsyncIO
Classifier: Operating System :: MacOS :: MacOS X
Classifier: Operating System :: Microsoft :: Windows
Classifier: Operating System :: POSIX
Classifier: Development Status :: 3 - Alpha
Classifier: Framework :: aiohttp
License-File: LICENSE
Requires-Dist: aiohttp>=3.9
Dynamic: author
Dynamic: author-email
Dynamic: classifier
Dynamic: description
Dynamic: description-content-type
Dynamic: home-page
Dynamic: license
Dynamic: requires-dist
Dynamic: summary
